zhtml/__init__.py
zhtml/zhtml.py
zhtml-1.1.1.dist-info/METADATA
zhtml-1.1.1.dist-info/WHEEL
zhtml-1.1.1.dist-info/top_level.txt
zhtml-1.1.1.dist-info/RECORD
