Metadata-Version: 2.1
Name: zhtml
Version: 1.1.1
Summary: Because the world needs yet another HTML templating framework
Home-page: https://gitlab.com/z3c0/zhtml
Author: z3c0
Author-email: z3c0@21337.tech
License: LGPL-3.0
Requires-Python: >=3.9
